fake_s3/__init__.py
fake_s3/__main__.py
fake_s3/file_store.py
fake_s3/main.py
fake_s3/s3_responses.py
fake_s3-1.0.2.dist-info/LICENSE
fake_s3-1.0.2.dist-info/METADATA
fake_s3-1.0.2.dist-info/WHEEL
fake_s3-1.0.2.dist-info/entry_points.txt
fake_s3-1.0.2.dist-info/RECORD
