Metadata-Version: 2.1
Name: fake-s3
Version: 1.0.2
Summary: A python port of Fake-S3.
License: MIT
Author: RuslanUC
Author-email: dev_ruslan_uc@protonmail.com
Requires-Python: >=3.8,<4.0
Classifier: Environment :: Console
Classifier: Intended Audience :: Developers
Classifier: License :: OSI Approved :: MIT License
Classifier: Operating System :: OS Independent
Classifier: Programming Language :: Python
Classifier: Programming Language :: Python :: 3
Classifier: Programming Language :: Python :: 3.8
Classifier: Programming Language :: Python :: 3.9
Classifier: Programming Language :: Python :: 3.10
Classifier: Programming Language :: Python :: 3.11
Classifier: Programming Language :: Python :: 3.7
Requires-Dist: aiofiles (>=23.1.0)
Requires-Dist: click (>=8.1.3)
Requires-Dist: python-magic (>=0.4.27)
Requires-Dist: quart (>=0.19.4)
Requires-Dist: uvicorn (>=0.27.1)
Project-URL: Homepage, https://github.com/RuslanUC/Fake-S3
Project-URL: Repository, https://github.com/RuslanUC/Fake-S3
